tree_sitter_svelte/__init__.py
tree_sitter_svelte/__init__.pyi
tree_sitter_svelte/_binding.pyd
tree_sitter_svelte/binding.c
tree_sitter_svelte/py.typed
tree_sitter_svelte/queries/folds.scm
tree_sitter_svelte/queries/highlights.scm
tree_sitter_svelte/queries/indents.scm
tree_sitter_svelte/queries/injections.scm
tree_sitter_svelte/queries/locals.scm
tree_sitter_svelte-1.0.2.dist-info/LICENSE
tree_sitter_svelte-1.0.2.dist-info/METADATA
tree_sitter_svelte-1.0.2.dist-info/WHEEL
tree_sitter_svelte-1.0.2.dist-info/top_level.txt
tree_sitter_svelte-1.0.2.dist-info/RECORD
